{
    "version": 10,
    "sections": [
        {
            "magic": "pat1",
            "id": 5,
            "groups": [],
            "name": "blue_color",
            "start frame": 30,
            "end frame": 59,
            "descending bind": true,
        },
        {
            "magic": "pai1",
            "frame count": 29,
            "loop": true,
            "tpls": [],
            "contents": [
                {
                    "name": "position",
                    "kind": "material",
                    "animations": [
                        {
                            "magic": "RLMC",
                            "targets": [
                                {
                                    "id": 0,
                                    "kind": "tev color 0 color r",
                                    "curve type": "hermite",
                                    "keys": [
                                        {
                                            "frame": 0.0,
                                            "value": 0.0,
                                            "slope": 0.0,
                                        },
                                    ],
                                },
                                {
                                    "id": 0,
                                    "kind": "tev color 0 color g",
                                    "curve type": "hermite",
                                    "keys": [
                                        {
                                            "frame": 0.0,
                                            "value": 0.0,
                                            "slope": 0.0,
                                        },
                                    ],
                                },
                                {
                                    "id": 0,
                                    "kind": "tev color 0 color b",
                                    "curve type": "hermite",
                                    "keys": [
                                        {
                                            "frame": 0.0,
                                            "value": 100.0,
                                            "slope": 0.0,
                                        },
                                    ],
                                },
                                {
                                    "id": 0,
                                    "kind": "tev color 1 color r",
                                    "curve type": "hermite",
                                    "keys": [
                                        {
                                            "frame": 0.0,
                                            "value": 60.0,
                                            "slope": 0.0,
                                        },
                                    ],
                                },
                                {
                                    "id": 0,
                                    "kind": "tev color 1 color g",
                                    "curve type": "hermite",
                                    "keys": [
                                        {
                                            "frame": 0.0,
                                            "value": 160.0,
                                            "slope": 0.0,
                                        },
                                    ],
                                },
                                {
                                    "id": 0,
                                    "kind": "tev color 1 color b",
                                    "curve type": "hermite",
                                    "keys": [
                                        {
                                            "frame": 0.0,
                                            "value": 255.0,
                                            "slope": 0.0,
                                        },
                                    ],
                                },
                                {
                                    "id": 0,
                                    "kind": "tev color 1 color a",
                                    "curve type": "hermite",
                                    "keys": [
                                        {
                                            "frame": 0.0,
                                            "value": 255.0,
                                            "slope": 0.0,
                                        },
                                    ],
                                },
                                {
                                    "id": 0,
                                    "kind": "tev konst 3 color a",
                                    "curve type": "hermite",
                                    "keys": [
                                        {
                                            "frame": 1.0,
                                            "value": 255.0,
                                            "slope": 0.0,
                                        },
                                    ],
                                },
                            ],
                        },
                    ],
                },
                {
                    "name": "position_l_00",
                    "kind": "material",
                    "animations": [
                        {
                            "magic": "RLMC",
                            "targets": [
                                {
                                    "id": 0,
                                    "kind": "tev color 0 color r",
                                    "curve type": "hermite",
                                    "keys": [
                                        {
                                            "frame": 0.0,
                                            "value": 193.0,
                                            "slope": -2.066667,
                                        },
                                        {
                                            "frame": 29.0,
                                            "value": 193.0,
                                            "slope": 2.066667,
                                        },
                                    ],
                                },
                                {
                                    "id": 0,
                                    "kind": "tev color 0 color g",
                                    "curve type": "hermite",
                                    "keys": [
                                        {
                                            "frame": 0.0,
                                            "value": 193.0,
                                            "slope": 0.0,
                                        },
                                    ],
                                },
                                {
                                    "id": 0,
                                    "kind": "tev color 0 color b",
                                    "curve type": "hermite",
                                    "keys": [
                                        {
                                            "frame": 0.0,
                                            "value": 255.0,
                                            "slope": 0.0,
                                        },
                                    ],
                                },
                                {
                                    "id": 0,
                                    "kind": "tev color 1 color r",
                                    "curve type": "hermite",
                                    "keys": [
                                        {
                                            "frame": 0.0,
                                            "value": 193.0,
                                            "slope": -2.066667,
                                        },
                                        {
                                            "frame": 29.0,
                                            "value": 193.0,
                                            "slope": 2.066667,
                                        },
                                    ],
                                },
                                {
                                    "id": 0,
                                    "kind": "tev color 1 color g",
                                    "curve type": "hermite",
                                    "keys": [
                                        {
                                            "frame": 0.0,
                                            "value": 193.0,
                                            "slope": 0.0,
                                        },
                                    ],
                                },
                                {
                                    "id": 0,
                                    "kind": "tev color 1 color b",
                                    "curve type": "hermite",
                                    "keys": [
                                        {
                                            "frame": 0.0,
                                            "value": 255.0,
                                            "slope": 0.0,
                                        },
                                    ],
                                },
                                {
                                    "id": 0,
                                    "kind": "tev konst 3 color a",
                                    "curve type": "hermite",
                                    "keys": [
                                        {
                                            "frame": 1.0,
                                            "value": 255.0,
                                            "slope": 0.0,
                                        },
                                    ],
                                },
                            ],
                        },
                    ],
                },
            ],
        },
    ],
}